{
  "schema_version": "1.0",
  "generation_timestamp_utc": "2025-08-16T18:39:13Z",
  "generator_note": "Refined manifest: added onboarding & (optional) README, fixed dec_ref placeholders, standardized mutable_policy for adopted lint spec. All existing entries preserved; only additive or metadata corrections before first hash seal.",
  "files": [
    {
      "path": "docs/roadmap/roadmap-master-v1.md",
      "version": "1.0.0",
      "dec_ref": "DEC-20250815-01",
      "hash_sha256": "10a48752eb09ccf77cd9efb4dd04c4bc59ec9caf611343d1e585ee6f36ddc0a6",
      "integrity_class": "roadmap",
      "mutable_policy": "append-only",
      "next_change_requires_dec": true,
      "notes": "Baseline roadmap; future evolution via delta files."
    },
    {
      "path": "docs/governance/signature-pipeline-plan-v1.md",
      "version": "1.0.0",
      "dec_ref": "DEC-20250813-02 (draft)",
      "hash_sha256": "2b673d3ae845a6f68f3c7e4d093aa27d1e61e837fb28a9637d3052e07ddf396f",
      "integrity_class": "signature-design",
      "mutable_policy": "append-only",
      "next_change_requires_dec": true,
      "notes": "Signature pipeline design (S0). Draft until adoption DEC finalized."
    },
    {
      "path": "docs/governance/dec/DEC-20250813-02-signature-pipeline-adoption.md",
      "version": "1.0.0",
      "dec_ref": "SELF",
      "hash_sha256": "d1a2c7e22462e2376367e510dd971461f5403541d5e6980d36bb873ddfc27604",
      "integrity_class": "decision",
      "mutable_policy": "immutable",
      "next_change_requires_dec": false,
      "notes": "Draft DEC for phased Ed25519 evidence signing (S0). Status changes on adoption."
    },
    {
      "path": "docs/fairness/hysteresis-config-v1.yml",
      "version": "1.0.0",
      "dec_ref": "DEC-20250815-02",
      "hash_sha256": "9e82b96bdbd336b225e44c829fc3e0ef4b620d8362a51862d66526570151fbf0",
      "integrity_class": "config",
      "mutable_policy": "locked-by-config-hash",
      "next_change_requires_dec": true,
      "notes": "Parameters governed by hysteresis.params.lock policy."
    },
    {
      "path": "docs/fairness/hysteresis-public-methodology-fragment-v1.md",
      "version": "1.0.0",
      "dec_ref": "DEC-20250812-02 + DEC-20250813-04",
      "hash_sha256": "5d7e72d48a753f568c87dee24bd139c705d6066e32cc1753aab9cdb7d1829a1f",
      "integrity_class": "public-methodology",
      "mutable_policy": "delta-via-dec",
      "next_change_requires_dec": true,
      "notes": "Public fairness narrative fragment (editorial disclaimer addition under DEC-20250813-04)."
    },
    {
      "path": "docs/fairness/hysteresis-state-machine-transitions.md",
      "version": "1.0.0",
      "dec_ref": "DEC-20250812-02",
      "hash_sha256": "c6eb0fe8da6d7e6fe5e1de3524ba834a2cb290fa9bb85ab6d614198b31ba3af9",
      "integrity_class": "spec-detail",
      "mutable_policy": "append-only",
      "next_change_requires_dec": true,
      "notes": "Concrete transitions; future param changes add new DEC reference."
    },
    {
      "path": "docs/governance/dec/DEC-20250812-02-hysteresis-adoption.md",
      "version": "1.0.0",
      "dec_ref": "SELF",
      "hash_sha256": "009825b624cca02c93e2ad500bafcdebf3ffc3adbf5a98c7cdbbde5334a79e38",
      "integrity_class": "decision",
      "mutable_policy": "immutable",
      "next_change_requires_dec": false,
      "notes": "DEC file itself; superseded only by later DEC referencing this id."
    },
    {
      "path": "docs/governance/dec/DEC-20250812-03-principles-reference-activation.md",
      "version": "1.0.0",
      "dec_ref": "SELF",
      "hash_sha256": "d86f59ce838c19f964a66938c863bf700a0b1ab340146b3ef26f7ec92578700d",
      "integrity_class": "decision",
      "mutable_policy": "immutable",
      "next_change_requires_dec": false,
      "notes": "Activation DEC for principles.reference lint & hash sealing enforcement."
    },
    {
      "path": "docs/governance/README-decision-log-process.md",
      "version": "1.0.0",
      "dec_ref": null,
      "hash_sha256": "874720bd571fabb9c77f7f09cff8d613b17694966c5ea5dfe22c2ae0652f2282",
      "integrity_class": "process",
      "mutable_policy": "append-only",
      "next_change_requires_dec": true,
      "notes": "Decision log process overview."
    },
    {
      "path": "docs/governance/lint-principles-reference-spec-v1.md",
      "version": "1.0.0",
      "dec_ref": "DEC-20250812-03",
      "hash_sha256": "902c9687e756516c99a127264b3a308b294b6f0aa0689fd58be823ac3e8ff765",
      "integrity_class": "lint-spec",
      "mutable_policy": "append-only",
      "next_change_requires_dec": true,
      "notes": "Adopted rules; modifications require DEC."
    },
    {
      "path": "docs/governance/todo-post-DEC-20250812-02.md",
      "version": "1.0.0",
      "dec_ref": "DEC-20250812-02",
      "hash_sha256": "a0ddcd6c86236320b438cc844ec96bac1ac6fb516c2f6f99628cf8903c02ebcd",
      "integrity_class": "action-list",
      "mutable_policy": "snapshot-then-new-file",
      "next_change_requires_dec": false,
      "notes": "Will spawn follow-up file rather than edit when tasks close."
    },
    {
      "path": "docs/governance/audit/pr-template-line-audit-2025-08-12T0509Z.md",
      "version": "1.0.0",
      "dec_ref": null,
      "hash_sha256": "d58b84e4ff4fda71fa332832f67a7d86795c16897016ba374470ffb19a0083b0",
      "integrity_class": "audit",
      "mutable_policy": "immutable",
      "next_change_requires_dec": false,
      "notes": "Each audit capture is immutable; new capture => new file."
    },
    {
      "path": ".github/pull_request_template.md",
      "version": "1.0.0",
      "dec_ref": "DEC-20250812-02 + DEC-20250812-03",
      "hash_sha256": "e86cc749ff0b9046b2cfee679e7843f2beeb83a34e99b05fbb79a97cdc41baf6",
      "integrity_class": "workflow-template",
      "mutable_policy": "append-only",
      "next_change_requires_dec": true,
      "notes": "Sections 26–37 with AUTO markers; modifications require DEC."
    },
    {
      "path": "docs/master-spec-deltas/delta-master-spec-v2-DEC-20250812-02.md",
      "version": "1.0.0",
      "dec_ref": "DEC-20250812-02",
      "hash_sha256": "93c6f7b2ee54176794cc838c89c2a66b020b08489f633f3610671d143d708d3e",
      "integrity_class": "delta",
      "mutable_policy": "immutable",
      "next_change_requires_dec": false,
      "notes": "Delta file; new changes create additional delta files."
    },
    {
      "path": "docs/master-spec-deltas/delta-master-spec-v2-DEC-20250813-06-event-schema-alignment.md",
      "version": "1.0.0",
      "dec_ref": "DEC-20250813-06",
      "hash_sha256": "8888305712149d6944d0e7cf8dc862692cd6467b1f8941bc9b75b4323c25cb5f",
      "integrity_class": "delta",
      "mutable_policy": "immutable",
      "next_change_requires_dec": false,
      "notes": "Aligns Master Spec §27 anchor text with canonical Event Schema v1.0 (editorial)."
    },
    {
      "path": "docs/principles/GP1-GP10-index.md",
      "version": "1.0.0",
      "dec_ref": null,
      "hash_sha256": "c85a58ce07f4ef4287bd08a3522c1317b4662302278144bef5f6b9b900d140b0",
      "integrity_class": "principles-index",
      "mutable_policy": "append-only",
      "next_change_requires_dec": true,
      "notes": "Index only; Master Spec remains source of truth."
    },
    {
      "path": "docs/privacy/pii-pattern-library-v1.md",
      "version": "1.0.0",
      "dec_ref": null,
      "hash_sha256": "bd47dc637362529a6f6bd9243468e6374ea25eaacfee5e9d21380b3a2e18c3ed",
      "integrity_class": "privacy-spec",
      "mutable_policy": "delta-via-dec",
      "next_change_requires_dec": true,
      "notes": "Pattern changes require DEC referencing performance metrics."
    },
    {
      "path": "docs/analytics/dashboard-widgets-hysteresis-initial.md",
      "version": "1.0.0",
      "dec_ref": null,
      "hash_sha256": "0d411afe729a8f5894c00811fca70da23cbb9a43123b549292e9df2db7f24a5b",
      "integrity_class": "analytics-spec",
      "mutable_policy": "append-only",
      "next_change_requires_dec": false,
      "notes": "Widget baseline; KPI shifts may add new version."
    },
    {
      "path": "docs/tests/hysteresis-test-plan-v1.md",
      "version": "1.0.0",
      "dec_ref": "DEC-20250812-02 + DEC-20250816-01",
      "hash_sha256": "0e13b0ef1f2c9f1c3a9ba346a4cad260b1f331521c98e077c10cc8cae6a7d2ca",
      "integrity_class": "test-plan",
      "mutable_policy": "append-only",
      "next_change_requires_dec": false,
      "notes": "Execution status appended; plan body preserved."
    },
    {
      "path": "docs/faq/faq-fairness-hysteresis-update.md",
      "version": "1.0.0",
      "dec_ref": "DEC-20250812-02 + DEC-20250813-04 + DEC-20250813-06",
      "hash_sha256": "abf20dade62bb4c984606fd4aed226fae2bb0f4d08d01fdb04e6c8d12f096418",
      "integrity_class": "faq",
      "mutable_policy": "append-only",
      "next_change_requires_dec": true,
      "notes": "FAQ updated editorially (disclaimer presence + safe context) under DEC-20250813-04."
    },
    {
      "path": "docs/status/progress-recap-latest-2025-08-12T035901Z.md",
      "version": "1.0.0",
      "dec_ref": null,
      "hash_sha256": "3dddc450215690be850060c1f194f838179e1e31622f39df71b1e2b652c24c83",
      "integrity_class": "status-recap",
      "mutable_policy": "immutable",
      "next_change_requires_dec": false,
      "notes": "New recap => new file (timestamped)."
    },
    {
      "path": "docs/governance/disclaimers-lint-spec-v1.md",
      "version": "1.0.0",
      "dec_ref": "DEC-20250813-04 + DEC-20250813-06",
      "hash_sha256": "862de8ced61bb931e5883c2abbdb21debe122bff8a5ad6f7be8c1fd1d9c88214",
      "integrity_class": "lint-spec",
      "mutable_policy": "delta-via-dec",
      "next_change_requires_dec": true,
      "notes": "Updated to describe whitelist safe-context handling (editorial)."
    },
    {
      "path": "docs/integrity/credential-schema-final-v1.md",
      "version": "1.0.0",
      "dec_ref": "DEC-20250813-04 + DEC-20250813-06",
      "hash_sha256": "fcc99046388814434bf38391c9806bef607a94619c6afee0550c6128fd9e0770",
      "integrity_class": "schema",
      "mutable_policy": "versioned",
      "next_change_requires_dec": true,
      "notes": "Editorial disclaimer / clarification only; no structural field change."
    },
    {
      "path": "docs/analytics/event-schema-canonical-v1.md",
      "version": "1.0.0",
      "dec_ref": "DEC-20250816-01",
      "hash_sha256": "b33cf1a9b6425f3da5d0b61184ac1818dcd196369fba11755406551235eef2b7",
      "integrity_class": "schema",
      "mutable_policy": "versioned",
      "next_change_requires_dec": true,
      "notes": "Canonical event schema baseline v1."
    },
    {
      "path": "docs/master-spec/master-spec-v2.0.md",
      "version": "2.0.0",
      "dec_ref": null,
      "hash_sha256": "c8990d9aa511904841036a69ff9cd265e7bd8e876d0f6d25327041d28633a0e7",
      "integrity_class": "master-spec",
      "mutable_policy": "delta-files",
      "next_change_requires_dec": true,
      "notes": "Master Spec baseline; changes only through delta files."
    },
    {
      "path": "docs/transparency/changelog-excerpt-phase1.5.md",
      "version": "0.1.0",
      "dec_ref": "DEC-20250813-04 + DEC-20250813-06",
      "hash_sha256": "48aaa087b8a605c62f27d3e3a189388289d2443fff5c5d5326165ed89b4671d5",
      "integrity_class": "transparency-placeholder",
      "mutable_policy": "append-only",
      "next_change_requires_dec": false,
      "notes": "Disclaimer block insertion only."
    },
    {
      "path": "docs/governance/policy-index-v1.md",
      "version": "1.0.0",
      "dec_ref": "DEC-20250812-03 + DEC-20250813-04 + DEC-20250813-06 + DEC-20250815-01",
      "hash_sha256": "4db33c5334268c832ed8b56a525ffc2deb287bf8eb82e80f4601f6fa5b92c1db",
      "integrity_class": "policy-index",
      "mutable_policy": "append-only",
      "next_change_requires_dec": true,
      "notes": "Index updated editorially for disclaimer governance alignment."
    },
    {
      "path": "docs/archive/fairness_equity-hysteresis-options-v1.md",
      "version": "1.0.0",
      "dec_ref": "DEC-20250812-02",
      "hash_sha256": "e988850b5663904b4e34b536966f425552d406893704a78a28021bf9985a7173",
      "integrity_class": "archive-spec",
      "mutable_policy": "immutable",
      "next_change_requires_dec": false,
      "notes": "Historical hysteresis option exploration (A–F)."
    },
    {
      "path": "docs/archive/ux_public-multipage-experience-master-spec-v2.md",
      "version": "1.0.0",
      "dec_ref": null,
      "hash_sha256": "bd8b8eeb3048a09d6d389a634d9aa6c2a40ec15d4a3facffe2d9cc4c9185174b",
      "integrity_class": "archive-ux-spec",
      "mutable_policy": "immutable",
      "next_change_requires_dec": false,
      "notes": "Historical UX multipage composite spec."
    },
    {
      "path": "docs/governance/trace/archive-trace-index-v1.md",
      "version": "1.0.0",
      "dec_ref": "DEC-20250815-03",
      "hash_sha256": "9f0f3fda88804c0a1766cf77eed09ab466d1783a52e6640479e17125e1fe69e4",
      "integrity_class": "trace-index",
      "mutable_policy": "append-only",
      "next_change_requires_dec": true,
      "notes": "Maps archived exploratory documents to canonical active specs."
    },
    {
      "path": "docs/onboarding/agent-bootstrap-manifest.md",
      "version": "1.0.0",
      "dec_ref": null,
      "hash_sha256": "8396ff215a5a4fb841564f382091844b5d19e3982b74255baf66241931aefc94",
      "integrity_class": "onboarding-spec",
      "mutable_policy": "append-only",
      "next_change_requires_dec": false,
      "notes": "Bootstrap for new agents; additive evolution only."
    },
    {
      "path": "README.md",
      "version": "1.0.0",
      "dec_ref": "DEC-20250813-04 + DEC-20250813-06 + DEC-20250815-01 + DEC-20250816-01",
      "hash_sha256": "037e4c39ad66608051212de96eb0bd28f11eca1bdd5570220f932b88537b3bfc",
      "integrity_class": "repository-readme",
      "mutable_policy": "append-only",
      "next_change_requires_dec": true,
      "notes": "Editorial disclaimer embedding; no policy semantics changed."
    },
    {
      "path": "docs/governance/dec/DEC-20250812-04-governance-baseline-thresholds.md",
      "version": "1.0.0",
      "dec_ref": "SELF",
      "hash_sha256": "fce2c9404bfa4401cd67761649c7829b586acbeda5a7330b67e7f4f1cb566ef2",
      "integrity_class": "decision",
      "mutable_policy": "immutable",
      "next_change_requires_dec": false,
      "notes": "Ratifikasi consolidated baseline thresholds (multi-category PII, evidence hash display length, terminology trigger, revocation codes, truncation decimals, min aggregation)."
    },
    {
      "path": "docs/integrity/evidence-minimum-phase1.5-v1.md",
      "version": "1.0.0",
      "dec_ref": null,
      "hash_sha256": "d2be6452ff04d67d7072a7889b0fdf0daf969773c794679e057fa03a257fb08a",
      "integrity_class": "evidence-policy",
      "mutable_policy": "append-only",
      "next_change_requires_dec": true,
      "notes": "Phase 1.5 Evidence Minimum Set definition (draft until ratified)."
    },
    {
      "path": "docs/governance/dec/DEC-20250813-01-known-debt-register.md",
      "version": "1.0.0",
      "dec_ref": "SELF",
      "hash_sha256": "15b4eb65659e5f484035a3bceeb85c381b7b0a3027c09c79b74565f82c608075",
      "integrity_class": "decision",
      "mutable_policy": "immutable",
      "next_change_requires_dec": false,
      "notes": "Known Debt & Deferred Controls Register (deferred subsystems & mitigations)."
    },
    {
      "path": "docs/onboarding/agent-role-policy-v1.md",
      "version": "1.0.0",
      "dec_ref": null,
      "hash_sha256": "54c8e6f8accadec136e63d8bc01a3a49bdc37ae82853d7821bdf22d83b1c9ec0",
      "integrity_class": "role-policy",
      "mutable_policy": "append-only",
      "next_change_requires_dec": true,
      "notes": "Agent role guard rails; amendments require DEC referencing this policy."
    },
    {
      "path": "docs/onboarding/agent-guardrails-v1.md",
      "version": "1.0.0",
      "dec_ref": null,
      "hash_sha256": "b2fb489583990747158cd165cb38073b912e09eafa724f43bb87de6fc901ad7d",
      "integrity_class": "guardrails-spec",
      "mutable_policy": "append-only",
      "next_change_requires_dec": true,
      "notes": "Operational guardrails for automation agents (bootstrap)."
    },
    {
      "path": "docs/governance/dec/DEC-20250813-03-disclaimers-presence-enforcement.md",
      "version": "1.0.0",
      "dec_ref": "SELF",
      "hash_sha256": "d82cb3f360fdbc944284fb98666d7d7acb7ac2a1702a33f11d1d26016415d7cb",
      "integrity_class": "decision",
      "mutable_policy": "immutable",
      "next_change_requires_dec": false,
      "notes": "Activation DEC for disclaimers presence enforcement Phase 2 trigger."
    },
    {
      "path": "docs/governance/dec/DEC-20250813-04-text-normalization-disclaimers-whitelist.md",
      "version": "1.0.0",
      "dec_ref": "SELF",
      "hash_sha256": "e6f4abe53178c6dcac31b9fba5b53c6f822f36f949fce8b6df934007af9770bd",
      "integrity_class": "decision",
      "mutable_policy": "immutable",
      "next_change_requires_dec": false,
      "notes": "Editorial normalization & whitelist alignment batch (no semantic change)."
    },
    {
      "path": "content/disclaimers/config.yml",
      "version": "1.0.0",
      "dec_ref": "DEC-20250813-04",
      "hash_sha256": "410994c10012167398154ef473c804213a6a3c2b5c69f01de2c384582476a25a",
      "integrity_class": "lint-config",
      "mutable_policy": "append-only",
      "next_change_requires_dec": true,
      "notes": "Whitelist safe contexts & thresholds for disclaimers lint."
    },
    {
      "path": "tools/fairness/engine-core.js",
      "version": "1.0.0",
      "dec_ref": "DEC-20250812-02",
      "hash_sha256": "082aa01b00eb14d52105af45361bd2cd1a5aafdde2c815f0d37dcda39129fd1d",
      "integrity_class": "fairness-engine-core",
      "mutable_policy": "append-only",
      "next_change_requires_dec": true,
      "notes": "Core hysteresis decide() logic extracted Wave 1; governed by original hysteresis adoption DEC."
    },
    {
      "path": "docs/integrity/gating-policy-v1.json",
      "version": "1.0.0",
      "dec_ref": "DEC-20250812-04 + DEC-20250813-05 + DEC-20250813-07",
      "hash_sha256": "ec038c5c51747836c13b455b183a9ecf7fb90a7de2e1cbc92d777c25eb3ab836",
      "integrity_class": "gating-policy",
      "mutable_policy": "append-only",
      "next_change_requires_dec": true,
      "notes": "Wave 1 gating thresholds (hype zero-tolerance, spec hash strict, param PASS required)."
    },
    {
      "path": "docs/governance/dec/DEC-20250813-07-hype-threshold-transition.md",
      "version": "1.0.0",
      "dec_ref": "SELF",
      "hash_sha256": "578782e6bc0c71a62eea7b1c905deb3fd0e77fa54fe3510a8ad5d198a34541a2",
      "integrity_class": "decision",
      "mutable_policy": "immutable",
      "next_change_requires_dec": false,
      "notes": "Transitional hype threshold segmentation (Wave 1.1)."
    },
    {
      "path": "docs/governance/dec/DEC-style-guide-v1.md",
      "version": "1.0.0",
      "dec_ref": null,
      "hash_sha256": "55c77fb8c21f4cf0474e5923268268d64e8fc13ac95bd392066e290d3a0a3441",
      "integrity_class": "decision-guidance",
      "mutable_policy": "immutable",
      "next_change_requires_dec": false,
      "notes": "Authoring style guide for DEC format standardization (superseded by v2)."
    },
    {
      "path": "docs/governance/dec/DEC-style-guide-v2.md",
      "version": "2.0.0",
      "dec_ref": null,
      "hash_sha256": "6568aa403b6e7bf3eb234b25e490a8c31dbffd55083b1e3b5ec19b196883eed9",
      "integrity_class": "decision-guidance",
      "mutable_policy": "immutable",
      "next_change_requires_dec": false,
      "notes": "Unified YAML-only DEC authoring style (v2)."
    },
    {
      "path": "docs/governance/dec/DEC-20250813-05-gating-policy-wave1-adoption.md",
      "version": "1.0.0",
      "dec_ref": "SELF",
      "hash_sha256": "2576903a6abe7e53f3efb2167721f6c1de049f2f163ed9e3b09f90cfd846da15",
      "integrity_class": "decision",
      "mutable_policy": "immutable",
      "next_change_requires_dec": false,
      "notes": "Adoption of Wave 1 gating policy thresholds & fairness engine core governance linkage."
    },
    {
      "path": "docs/governance/dec/DEC-20250813-06-consolidated-governed-edits.md",
      "version": "1.0.0",
      "dec_ref": "SELF",
      "hash_sha256": "db9faef0665c73072e5a3e5dea9104c0c6beaa8ec536d3c8ca32e8808683bcf4",
      "integrity_class": "decision",
      "mutable_policy": "immutable",
      "next_change_requires_dec": false,
      "notes": "Retroactive authorization consolidation for governed editorial / whitelist alignment edits (Wave 1)."
    },
    {
      "path": "docs/governance/dec/DEC-20250813-08-evidence-hash-display-length.md",
      "version": "1.0.0",
      "dec_ref": "SELF",
      "hash_sha256": "4f6e69897f7059acac0282537e0f1a97e13cebf7731be6344b8bea14331034b9",
      "integrity_class": "decision",
      "mutable_policy": "immutable",
      "next_change_requires_dec": false,
      "notes": "Confirmation DEC for evidence hash UI prefix length (16 hex)."
    },
    {
      "path": "docs/governance/dec/DEC-20250813-09-equity-index-rounding.md",
      "version": "1.0.0",
      "dec_ref": "SELF",
      "hash_sha256": "0485aec829b32e77a144d085a0b388c8fc5b74620dfe978874702df7723da698",
      "integrity_class": "decision",
      "mutable_policy": "immutable",
      "next_change_requires_dec": false,
      "notes": "Rounding precision DEC (equity index 2 decimals half-up)."
    },
    {
      "path": "docs/governance/dec/DEC-20250813-10-feedback-categories-canonical.md",
      "version": "1.0.0",
      "dec_ref": "SELF",
      "hash_sha256": "c209daae774250fa94bc04f95e8bfe9a30b9059b109fcd48c0f5faed3c0f4545",
      "integrity_class": "decision",
      "mutable_policy": "immutable",
      "next_change_requires_dec": false,
      "notes": "Adoption of canonical feedback categories (4-set)."
    },
    {
      "path": "policies/aggregation-min-cell.rego",
      "version": "0.1.0",
      "dec_ref": "DEC-20250812-04",
      "hash_sha256": "175fd1a42be113f392ce7f129072bc74ea1bb88a13453e8fbd51e01f1651a313",
      "integrity_class": "policy-rule",
      "mutable_policy": "append-only",
      "next_change_requires_dec": true,
      "notes": "OPA rule enforcing min cell aggregation threshold with DEC override."
    },
    {
      "path": "docs/fairness/equity-snapshot-pseudocode.md",
      "version": "0.1.0",
      "dec_ref": null,
      "hash_sha256": "74f6718c08e779626ee095d1f46f5aa53cb641d3719f9e79a82aaf8fbf71129e",
      "integrity_class": "pseudocode",
      "mutable_policy": "append-only",
      "next_change_requires_dec": true,
      "notes": "Draft pseudocode for equity snapshot computation (pre-implementation)."
    },
    {
      "path": "docs/integrity/verify-cli-doc-draft.md",
      "version": "0.1.0",
      "dec_ref": null,
      "hash_sha256": "b2f4ff66586b42cd6f09b262ba632e7243b8bf7ff251ec6625eaeb06129962b7",
      "integrity_class": "doc-draft",
      "mutable_policy": "append-only",
      "next_change_requires_dec": true,
      "notes": "Draft verification CLI usage instructions."
    },
    {
      "path": "docs/governance/dec/DEC-20250815-01-governed-editorial-maintenance.md",
      "version": "1.0.0",
      "dec_ref": "SELF",
      "hash_sha256": "3adde01d4a97546ce058eeb62f098d88a4aabb8f7e505c7a3e754669c742f10e",
      "integrity_class": "decision",
      "mutable_policy": "immutable",
      "next_change_requires_dec": false,
      "notes": "Editorial maintenance authorization for README, Roadmap, and Policy Index (2025-08-15)."
    },
    {
      "path": "docs/verify-cli.md",
      "version": "0.2.0",
      "dec_ref": null,
      "hash_sha256": "32576ec92b39725c53995580926b5bba2b724b77d5089f445498e48e0b973b30",
      "integrity_class": "verification-guide",
      "mutable_policy": "append-only",
      "next_change_requires_dec": true,
      "notes": "Public-facing verification guide (CLI). Editorial evolution allowed; semantic policy shifts require DEC."
    }
  ],
  "integrity_rules": {
    "immutable": "File content must never change; new adjustments require new file.",
    "append-only": "Only additive changes (new sections) allowed; no deletion of prior lines.",
    "delta-via-dec": "Any semantic change requires DEC and possibly new delta file.",
    "locked-by-config-hash": "Runtime enforcement via policy comparing config hash at build.",
    "activation-pending": "Spec present but not enforced until DEC adoption.",
    "versioned": "Semver increments required for structural changes.",
    "delta-files": "Master file static; changes captured in delta files referencing DEC."
  },
  "ci_expectations": {
    "hash_update_process": [
      "Compute hash for each path",
      "If '<PENDING_HASH>' and file exists -> replace with computed",
      "If hash changed without DEC where next_change_requires_dec=true -> FAIL",
      "Emit diff report artifact spec-hash-diff.json"
    ],
    "policy_links": {
      "hysteresis.params.lock": "docs/fairness/hysteresis-config-v1.yml",
      "principles.reference": "docs/governance/lint-principles-reference-spec-v1.md"
    },
    "enforcement_escalation": "principles.reference: WARN 48h → DENY"
  }
}
